Metadata-Version: 2.1
Name: flet-runtime
Version: 0.21.0
Summary: Flet Runtime - a base package for Flet desktop and Flet mobile.
License: Apache-2.0
Author: Appveyor Systems Inc.
Author-email: hello@flet.dev
Requires-Python: >=3.7,<4.0
Classifier: License :: OSI Approved :: Apache Software License
Classifier: Programming Language :: Python :: 3
Classifier: Programming Language :: Python :: 3.7
Classifier: Programming Language :: Python :: 3.8
Classifier: Programming Language :: Python :: 3.9
Classifier: Programming Language :: Python :: 3.10
Classifier: Programming Language :: Python :: 3.11
Classifier: Programming Language :: Python :: 3.12
Requires-Dist: flet-core (==0.21.0)
Requires-Dist: httpx (>=0.24.1,<0.25.0)
Requires-Dist: oauthlib (>=3.2.2,<4.0.0)
Requires-Dist: typing-extensions (>=4.6.2,<5.0.0) ; python_version < "3.8"
Project-URL: documentation, https://flet.dev/docs
Project-URL: homepage, https://flet.dev
Project-URL: repository, https://github.com/flet-dev/flet
